{
    "users": [ {
        "person": {
            "firstName": "Garry",
            "lastName": "Finch"
        },
        "jobTitle": "Front End Technical Lead",
        "twitter": "gazraa"
    }, {
        "person": {
            "firstName": "Garry",
            "lastName": "Finch"
        },
        "jobTitle": "Photographer",
        "twitter": "photobasics"
    }, {
        "person": {
            "firstName": "Garry",
            "lastName": "Finch"
        },
        "jobTitle": "LEGO Geek",
        "twitter": "minifigures"
    } ]
}
